.coveragerc
.editorconfig
.gitignore
.gitlab-ci.yml
AUTHORS.rst
CONTRIBUTING.rst
HISTORY.rst
LICENSE
MANIFEST.in
Makefile
README.rst
requirements_dev.txt
setup.cfg
setup.py
tox.ini
.github/ISSUE_TEMPLATE.md
docs/Makefile
docs/authors.rst
docs/conf.py
docs/contributing.rst
docs/history.rst
docs/index.rst
docs/installation.rst
docs/make.bat
docs/readme.rst
docs/usage.rst
docs/_build/html/_static/file.png
docs/_build/html/_static/minus.png
docs/_build/html/_static/plus.png
docs/images/S2A_RSRs.png
pyrsr/__init__.py
pyrsr/rsr.py
pyrsr/sensorspecs.py
pyrsr/version.py
pyrsr.egg-info/PKG-INFO
pyrsr.egg-info/SOURCES.txt
pyrsr.egg-info/dependency_links.txt
pyrsr.egg-info/not-zip-safe
pyrsr.egg-info/requires.txt
pyrsr.egg-info/top_level.txt
pyrsr/data/Aqua/MODIS/band_1
pyrsr/data/Aqua/MODIS/band_10
pyrsr/data/Aqua/MODIS/band_11
pyrsr/data/Aqua/MODIS/band_12
pyrsr/data/Aqua/MODIS/band_13
pyrsr/data/Aqua/MODIS/band_14
pyrsr/data/Aqua/MODIS/band_15
pyrsr/data/Aqua/MODIS/band_16
pyrsr/data/Aqua/MODIS/band_2
pyrsr/data/Aqua/MODIS/band_3
pyrsr/data/Aqua/MODIS/band_4
pyrsr/data/Aqua/MODIS/band_5
pyrsr/data/Aqua/MODIS/band_6
pyrsr/data/Aqua/MODIS/band_7
pyrsr/data/Aqua/MODIS/band_8
pyrsr/data/Aqua/MODIS/band_9
pyrsr/data/Aqua/MODIS/reference
pyrsr/data/Landsat-4/TM/band_1
pyrsr/data/Landsat-4/TM/band_2
pyrsr/data/Landsat-4/TM/band_3
pyrsr/data/Landsat-4/TM/band_4
pyrsr/data/Landsat-4/TM/band_5
pyrsr/data/Landsat-4/TM/band_6
pyrsr/data/Landsat-4/TM/band_7
pyrsr/data/Landsat-4/TM/reference
pyrsr/data/Landsat-5/TM/band_1
pyrsr/data/Landsat-5/TM/band_2
pyrsr/data/Landsat-5/TM/band_3
pyrsr/data/Landsat-5/TM/band_4
pyrsr/data/Landsat-5/TM/band_5
pyrsr/data/Landsat-5/TM/band_6
pyrsr/data/Landsat-5/TM/band_7
pyrsr/data/Landsat-5/TM/reference
pyrsr/data/Landsat-7/ETM+/band_1
pyrsr/data/Landsat-7/ETM+/band_2
pyrsr/data/Landsat-7/ETM+/band_3
pyrsr/data/Landsat-7/ETM+/band_4
pyrsr/data/Landsat-7/ETM+/band_5
pyrsr/data/Landsat-7/ETM+/band_6H
pyrsr/data/Landsat-7/ETM+/band_6L
pyrsr/data/Landsat-7/ETM+/band_7
pyrsr/data/Landsat-7/ETM+/band_8
pyrsr/data/Landsat-7/ETM+/reference
pyrsr/data/Landsat-8/OLI_TIRS/band_1
pyrsr/data/Landsat-8/OLI_TIRS/band_10
