Metadata-Version: 2.1
Name: pyrsr
Version: 0.7.0
Summary: A package providing relative spectral response functions for remote sensing instruments.
Home-page: https://git.gfz-potsdam.de/geomultisens/pyrsr
Author: Daniel Scheffler
Author-email: daniel.scheffler@gfz-potsdam.de
License: Apache-2.0
Keywords: pyrsr,relative spectral response,remote sensing,sensors
Platform: UNKNOWN
Classifier: Development Status :: 4 - Beta
Classifier: Intended Audience :: Developers
Classifier: License :: OSI Approved :: Apache Software License
Classifier: Natural Language :: English
Classifier: Programming Language :: Python :: 3.7
Classifier: Programming Language :: Python :: 3.8
Classifier: Programming Language :: Python :: 3.9
Classifier: Programming Language :: Python :: 3.10
Requires-Python: >=3.7
License-File: LICENSE
License-File: AUTHORS.rst
